image_classification_jax/.DS_Store
image_classification_jax/__init__.py
image_classification_jax/run_experiment.py
image_classification_jax/run_experiment_test.py
image_classification_jax/models/ViT.py
image_classification_jax/models/__init__.py
image_classification_jax/models/network_utils.py
image_classification_jax/models/resnet.py
image_classification_jax/utils/__init__.py
image_classification_jax/utils/imagenet_pipeline.py
image_classification_jax/utils/tf_preprocessing_tools.py
image_classification_jax/utils/training_utils.py
image_classification_jax-0.1.4.dist-info/LICENSE
image_classification_jax-0.1.4.dist-info/WHEEL
image_classification_jax-0.1.4.dist-info/METADATA
image_classification_jax-0.1.4.dist-info/RECORD
