Metadata-Version: 2.3
Name: image-classification-jax
Version: 0.1.4
Summary: Run image classification experiments in JAX with ViT, resnet, cifar10, cifar100, imagenette, and imagenet.
Keywords: python,machine learning,optimization,jax
Author: Evan Walters
Requires-Python: >=3.9
Classifier: Environment :: Console
Classifier: Programming Language :: Python
Classifier: Intended Audience :: Developers
Classifier: Operating System :: OS Independent
Classifier: Programming Language :: Python :: 3
Classifier: Intended Audience :: Science/Research
Classifier: Development Status :: 4 - Beta
Classifier: License :: OSI Approved :: MIT License
Classifier: Topic :: Scientific/Engineering :: Artificial Intelligence
Classifier: Topic :: Software Development :: Libraries :: Python Modules
Requires-Dist: jax
Requires-Dist: flax
Requires-Dist: einops
Requires-Dist: optax
Requires-Dist: numpy
Requires-Dist: tensorflow-cpu
Requires-Dist: tensorflow-datasets
Requires-Dist: wandb
Requires-Dist: psgd-jax
Project-URL: homepage, https://github.com/evanatyourservice/image-classification-jax
Project-URL: repository, https://github.com/evanatyourservice/image-classification-jax
